{
  "00000000" : {
    "id" : "00000000",
    "major" : "none",
    "name" : "none none",
    "nickname" : "none",
    "status" : "non",
    "tel" : "000-000-0000"
  },
  "61410013" : {
    "id" : "61410013",
    "major" : "คอมพิวเตอร์",
    "name" : "กนกวรรณ มูลชัย",
    "nickname" : "ออย",
    "tel" : "06-5416-7488"
  },
  "61410143" : {
    "id" : "61410143",
    "major" : "ฟิสิกส์",
    "name" : "กษิดิ์เดช ขอนยาง",
    "nickname" : "-",
    "tel" : "-"
  },
  "61410150" : {
    "id" : "61410150",
    "major" : "ชีววิทยา",
    "name" : "กัญญ์วรา ขันวิเศษ",
    "nickname" : "-",
    "tel" : "-"
  },
  "61410167" : {
    "id" : "61410167",
    "major" : "เทคโนโลยีและสื่อสารการศึกษา",
    "name" : "กัญญ์วรา สิงห์โต",
    "nickname" : "ตั๊กแตน",
    "tel" : "06-4891-7964"
  },
  "61410198" : {
    "id" : "61410198",
    "major" : "คอมพิวเตอร์",
    "name" : "กันตพงศ์ เจือจันทร์",
    "nickname" : "เคน",
    "tel" : "083-943-2206"
  },
  "61410204" : {
    "id" : "61410204",
    "major" : "คอมพิวเตอร์",
    "name" : "กันตพล ชัยวิรัตน์นุกูล",
    "nickname" : "เก้า",
    "tel" : "082-513-7136"
  },
  "61410211" : {
    "id" : "61410211",
    "major" : "เคมี",
    "name" : "กัลยรัตน์ บุญดัด",
    "nickname" : "จุ๊บแจง",
    "tel" : "06-2030-9140"
  },
  "61410297" : {
    "id" : "61410297",
    "major" : "ภาษาไทย",
    "name" : "กุลธรานันท์ ทาบาง",
    "nickname" : "แนน",
    "tel" : "091-291-0946"
  },
  "61410303" : {
    "id" : "61410303",
    "major" : "เทคโนโลยีและสื่อสารการศึกษา",
    "name" : "กุลนาถ แหวนสุข",
    "nickname" : "อุ้ม",
    "tel" : "092-995-2033"
  },
  "61410327" : {
    "id" : "61410327",
    "major" : "ภาษาอังกฤษ",
    "name" : "กุลภรณ์ เครือเพ่ง",
    "nickname" : "กุล",
    "tel" : "099-738-4927"
  },
  "61410457" : {
    "id" : "61410457",
    "major" : "ภาษาอังกฤษ",
    "name" : "จารุกิตต์ ช่างเกวียน",
    "nickname" : "อุ้ม",
    "tel" : "096-993-4199"
  },
  "61410488" : {
    "id" : "61410488",
    "major" : "พลศึกษาและวิทยาศาสตร์การออกกำลังกาย",
    "name" : "จิดาภา นาคภู่",
    "nickname" : "อั๊ง",
    "tel" : "094-724-9150"
  },
  "61410495" : {
    "id" : "61410495",
    "major" : "เคมี",
    "name" : "จิตรภาณุ โชติกะคาม",
    "nickname" : "กาย",
    "tel" : "080-660-5576"
  },
  "61410570" : {
    "id" : "61410570",
    "major" : "ภาษาไทย",
    "name" : "จีรนันท์ คำอ่าง",
    "nickname" : "นิว",
    "tel" : "097-950-7986"
  },
  "61410648" : {
    "id" : "61410648",
    "major" : "ชีววิทยา",
    "name" : "ฉัตร์รดา สารผล",
    "nickname" : "ปราย",
    "tel" : "095-169-0310"
  },
  "61410662" : {
    "id" : "61410662",
    "major" : "ภาษาไทย",
    "name" : "ชญาดา ศรีโคตร",
    "nickname" : "ออมสิน",
    "tel" : "06-1951-4416"
  },
  "61410686" : {
    "id" : "61410686",
    "major" : "คณิตศาสตร์",
    "name" : "ชญานันท์ คุ้มฉาย",
    "nickname" : "-",
    "tel" : "-"
  },
  "61410716" : {
    "id" : "61410716",
    "major" : "ชีววิทยา",
    "name" : "ชนม์นิภา กลายกลาง",
    "nickname" : "ขวัญ",
    "tel" : "090-837-7376"
  },
  "61410747" : {
    "id" : "61410747",
    "major" : "ภาษาไทย",
    "name" : "ชนิกา จอมคำ",
    "nickname" : "แท็ต",
    "tel" : "097-983-7669"
  },
  "61410785" : {
    "id" : "61410785",
    "major" : "เคมี",
    "name" : "ชยุตพนธ์ ตุ่มศิริ",
    "nickname" : "อาร์ม",
    "tel" : "098-784-4185"
  },
  "61410884" : {
    "id" : "61410884",
    "major" : "เคมี",
    "name" : "ชลิตา อำมลา",
    "nickname" : "แป้ง",
    "tel" : "06-4113-1105"
  },
  "61410914" : {
    "id" : "61410914",
    "major" : "เคมี",
    "name" : "ชวัลลักษณ์ สุขทอง",
    "nickname" : "แอมป์",
    "tel" : "082-829-7727"
  },
  "61410969" : {
    "id" : "61410969",
    "major" : "ภาษาไทย",
    "name" : "ชัญญานุช จันคำ",
    "nickname" : "ไหม",
    "tel" : "095-286-5122"
  },
  "61411072" : {
    "id" : "61411072",
    "major" : "ภาษาไทย",
    "name" : "ฐิตาพร ขอนทอง",
    "nickname" : "เบนซ์",
    "tel" : "099-610-7566"
  },
  "61411287" : {
    "id" : "61411287",
    "major" : "พลศึกษาและวิทยาศาสตร์การออกกำลังกาย",
    "name" : "ณัฐฐินันท์ ดวงใจ",
    "nickname" : "บีม",
    "tel" : "083-439-2021"
  },
  "61411294" : {
    "id" : "61411294",
    "major" : "คณิตศาสตร์",
    "name" : "ณัฐณิชา ใจปัญญา",
    "nickname" : "-",
    "tel" : "-"
  },
  "61411317" : {
    "id" : "61411317",
    "major" : "คณิตศาสตร์",
    "name" : "ณัฐธิดา น้อยเพ็ง",
    "nickname" : "การ์ตูน",
    "tel" : "096-417-5726"
  },
  "61411393" : {
    "id" : "61411393",
    "major" : "พลศึกษาและวิทยาศาสตร์การออกกำลังกาย",
    "name" : "ณัฐวุฒิ พาลิตา",
    "nickname" : "ไนน์",
    "tel" : "093-213-9090"
  },
  "61411409" : {
    "id" : "61411409",
    "major" : "เคมี",
    "name" : "ณัฐวุฒิ ไชยยศ",
    "nickname" : "นัท",
    "tel" : "082-970-8758"
  },
  "61411416" : {
    "id" : "61411416",
    "major" : "ภาษาอังกฤษ",
    "name" : "ณิชนันทน์ ภูวนารถ",
    "nickname" : "อาร์",
    "tel" : "094-428-2154"
  },
  "61411430" : {
    "id" : "61411430",
    "major" : "ภาษาไทย",
    "name" : "ณิชาพัชร์ แผ่จิตร",
    "nickname" : "บีม",
    "tel" : "090-749-1799"
  },
  "61411461" : {
    "id" : "61411461",
    "major" : "เคมี",
    "name" : "ตุลยวัต คุ้มสุวรรณ",
    "nickname" : "ตุลย์",
    "tel" : "095-790-7130"
  },
  "61411539" : {
    "id" : "61411539",
    "major" : "คอมพิวเตอร์",
    "name" : "ธนดล สุทธาพันธุ์",
    "nickname" : "ตะวัน",
    "tel" : "094-713-9119"
  },
  "61411553" : {
    "id" : "61411553",
    "major" : "ภาษาอังกฤษ",
    "name" : "ธนพิพัฒน์ แตงอ่ำ",
    "nickname" : "หลุยส์",
    "tel" : "091-839-4620"
  },
  "61411652" : {
    "id" : "61411652",
    "major" : "เทคโนโลยีและสื่อสารการศึกษา",
    "name" : "ธัญญารัตน์ เถรนอก",
    "nickname" : "โบว์",
    "tel" : "083-631-6973"
  },
  "61411843" : {
    "id" : "61411843",
    "major" : "เคมี",
    "name" : "ธีรภัทร ทักษะวิเรขะพันธ์",
    "nickname" : "โต้",
    "tel" : "095-946-0762"
  },
  "61411874" : {
    "id" : "61411874",
    "major" : "ภาษาไทย",
    "name" : "นงนภัส กาวงษ์กลาง",
    "nickname" : "ออม",
    "tel" : "082-315-0949"
  },
  "61411904" : {
    "id" : "61411904",
    "major" : "เคมี",
    "name" : "นภัส แสงสุวรรณ",
    "nickname" : "ปลากริม",
    "tel" : "082-538-4678"
  },
  "61411911" : {
    "id" : "61411911",
    "major" : "คณิตศาสตร์",
    "name" : "นภัสวรรณ จันทา",
    "nickname" : "ใบยา",
    "tel" : "098-801-6650"
  },
  "61411942" : {
    "id" : "61411942",
    "major" : "พลศึกษาและวิทยาศาสตร์การออกกำลังกาย",
    "name" : "นฤมลรัตน์ ห่วงเพชร",
    "nickname" : "นะมล",
    "tel" : "082-210-3791"
  },
  "61412147" : {
    "id" : "61412147",
    "major" : "คอมพิวเตอร์",
    "name" : "บัณฑิต โฉมศรี",
    "nickname" : "ออม",
    "tel" : "091-024-8161"
  },
  "61412154" : {
    "id" : "61412154",
    "major" : "ภาษาไทย",
    "name" : "บุญพิทักษ์ กรุณวงค์",
    "nickname" : "ส้มโอ",
    "tel" : "082-772-9474"
  },
  "61412161" : {
    "id" : "61412161",
    "major" : "เทคโนโลยีและสื่อสารการศึกษา",
    "name" : "บุษกร สีเชียงหา",
    "nickname" : "ไวน์",
    "tel" : "06-1268-0540"
  },
  "61412185" : {
    "id" : "61412185",
    "major" : "เทคโนโลยีและสื่อสารการศึกษา",
    "name" : "บุษยา น้อยนาค",
    "nickname" : "บีม",
    "tel" : "099-290-2525"
  },
  "61412277" : {
    "id" : "61412277",
    "major" : "ภาษาไทย",
    "name" : "ปพริมภรณ์ เสาสุขใจ",
    "nickname" : "พรีม",
    "tel" : "094-617-3450"
  },
  "61412505" : {
    "id" : "61412505",
    "major" : "เคมี",
    "name" : "พลกฤต กาทองทุ่ง",
    "nickname" : "ไกด์",
    "tel" : "091-069-9974"
  },
  "61412529" : {
    "id" : "61412529",
    "major" : "คณิตศาสตร์",
    "name" : "พัชรพงษ์ ยอดนวล",
    "nickname" : "เจมส์",
    "tel" : "082-181-6296"
  },
  "61412567" : {
    "id" : "61412567",
    "major" : "ภาษาอังกฤษ",
    "name" : "พิชญานัฐ ทัดพัฒนกุล",
    "nickname" : "-",
    "tel" : "-"
  },
  "61412734" : {
    "id" : "61412734",
    "major" : "คณิตศาสตร์",
    "name" : "เพียวเพชร เขมนิพัทธ์",
    "nickname" : "เพียว",
    "tel" : "095-640-9455"
  },
  "61412789" : {
    "id" : "61412789",
    "major" : "ภาษาไทย",
    "name" : "ภัณฑิรา จุลโพธิ์",
    "nickname" : "มีน",
    "tel" : "-"
  },
  "61412833" : {
    "id" : "61412833",
    "major" : "ภาษาอังกฤษ",
    "name" : "ภัทรานิษฐ์ ธัญญาพิทักษ์",
    "nickname" : "เปรี้ยว",
    "tel" : "088-156-5747"
  },
  "61412871" : {
    "id" : "61412871",
    "major" : "ภาษาไทย",
    "name" : "ภาณุมาส แสนใจวุฒิ",
    "nickname" : "ต่าย",
    "tel" : "087-314-3093"
  },
  "61412932" : {
    "id" : "61412932",
    "major" : "ภาษาอังกฤษ",
    "name" : "มนชนก สังข์จันทร์",
    "nickname" : "แบม",
    "tel" : "06-3197-0913"
  },
  "61413038" : {
    "id" : "61413038",
    "major" : "คณิตศาสตร์",
    "name" : "รวิสรา สมบูรณ์มา",
    "nickname" : "-",
    "tel" : "-"
  },
  "61413113" : {
    "id" : "61413113",
    "major" : "พลศึกษาและวิทยาศาสตร์การออกกำลังกาย",
    "name" : "รุ้งพราย หงษ์ขาวปูน",
    "nickname" : "ปุ๊ก",
    "tel" : "095-716-7635"
  },
  "61413144" : {
    "id" : "61413144",
    "major" : "ภาษาอังกฤษ",
    "name" : "เรืองริน บุญลอย",
    "nickname" : "พรรณ",
    "tel" : "096-048-1689"
  },
  "61413229" : {
    "id" : "61413229",
    "major" : "คอมพิวเตอร์",
    "name" : "วรเชษฐ์ แสงบุดดี",
    "nickname" : "เคน",
    "tel" : "098-003-1870"
  },
  "61413380" : {
    "id" : "61413380",
    "major" : "เคมี",
    "name" : "วิชญา ฉวีวงศ์พงษ์เดช",
    "nickname" : "แพรว",
    "tel" : "088-165-9039"
  },
  "61413625" : {
    "id" : "61413625",
    "major" : "ภาษาอังกฤษ",
    "name" : "ศุภาพิชญ์ นิธิกรโกศล",
    "nickname" : "หยก",
    "tel" : "06-1058-5824"
  },
  "61413694" : {
    "id" : "61413694",
    "major" : "คอมพิวเตอร์",
    "name" : "สาริษฐ์ ศรีใจ",
    "nickname" : "กองโต้",
    "tel" : "095-692-0962"
  },
  "61413762" : {
    "id" : "61413762",
    "major" : "เทคโนโลยีและสื่อสารการศึกษา",
    "name" : "สิรินันท์ แท่นจันทร์",
    "nickname" : "หนูนัน",
    "tel" : "094-823-4357"
  },
  "61413939" : {
    "id" : "61413939",
    "major" : "เทคโนโลยีและสื่อสารการศึกษา",
    "name" : "สุพรรณี เพ็ชรรอด",
    "nickname" : "วิว",
    "tel" : "06-2918-6091"
  },
  "61413977" : {
    "id" : "61413977",
    "major" : "ภาษาไทย",
    "name" : "สุภาวดี สีสุข",
    "nickname" : "ก้อย",
    "tel" : "06-4994-2215"
  },
  "61414134" : {
    "id" : "61414134",
    "major" : "คอมพิวเตอร์",
    "name" : "อนิรุธ หาญณรงค์",
    "nickname" : "ม่อน",
    "tel" : "096-841-5345"
  },
  "61414264" : {
    "id" : "61414264",
    "major" : "ภาษาไทย",
    "name" : "อริศรา สุสินนะ",
    "nickname" : "มิ้นท์",
    "tel" : "080-509-9881"
  },
  "counting" : 0
}
